gaana/__init__.py
gaana/api.py
gaana/cli.py
gaana/converter.py
gaana/downloader.py
gaana/errors.py
gaana/lyrics.py
gaana/main.py
gaana/metadata.py
gaana/printer.py
gaana/utils.py
gaanadl_cli-1.3.1.dist-info/licenses/LICENSE
gaanadl_cli-1.3.1.dist-info/METADATA
gaanadl_cli-1.3.1.dist-info/WHEEL
gaanadl_cli-1.3.1.dist-info/entry_points.txt
gaanadl_cli-1.3.1.dist-info/top_level.txt
gaanadl_cli-1.3.1.dist-info/RECORD
