Metadata-Version: 2.4
Name: gaanadl-cli
Version: 1.3.1
Summary: Download high-quality music from Gaana with metadata and synced lyrics
Home-page: https://github.com/notdeltaxd/gaanadl-cli
Author: notdelta_xd
License: MIT
Project-URL: Bug Reports, https://github.com/notdeltaxd/gaanadl-cli/issues
Project-URL: Source, https://github.com/notdeltaxd/gaanadl-cli
Keywords: gaana,music,downloader,cli,flac,lyrics
Classifier: Development Status :: 4 - Beta
Classifier: Environment :: Console
Classifier: Intended Audience :: End Users/Desktop
Classifier: License :: OSI Approved :: MIT License
Classifier: Operating System :: OS Independent
Classifier: Programming Language :: Python :: 3
Classifier: Programming Language :: Python :: 3.8
Classifier: Programming Language :: Python :: 3.9
Classifier: Programming Language :: Python :: 3.10
Classifier: Programming Language :: Python :: 3.11
Classifier: Programming Language :: Python :: 3.12
Classifier: Topic :: Multimedia :: Sound/Audio
Requires-Python: >=3.8
License-File: LICENSE
Requires-Dist: requests>=2.32.0
Requires-Dist: mutagen>=1.47.0
Requires-Dist: rich>=14.0.0
Requires-Dist: pathvalidate>=3.3.0
Requires-Dist: pyfiglet>=1.0.3
Dynamic: author
Dynamic: classifier
Dynamic: description
Dynamic: description-content-type
Dynamic: home-page
Dynamic: keywords
Dynamic: license
Dynamic: license-file
Dynamic: project-url
Dynamic: requires-dist
Dynamic: requires-python
Dynamic: summary
